pytdp/__init__.py
pytdp/TD/__init__.py
pytdp/TD/troublesomedata.py
pytdp/analyzer/__init__.py
pytdp/analyzer/api.py
pytdp/bases/__init__.py
pytdp/bases/api.py
pytdp/preprocessor/__init__.py
pytdp/preprocessor/api.py
pytdp/reader/__init__.py
pytdp/reader/api.py
PyTDP-1.0.3.dist-info/LICENSE
PyTDP-1.0.3.dist-info/METADATA
PyTDP-1.0.3.dist-info/WHEEL
PyTDP-1.0.3.dist-info/top_level.txt
PyTDP-1.0.3.dist-info/RECORD
