Metadata-Version: 2.1
Name: PyTDP
Version: 1.0.3
Summary: Makes troublesome data preprocessing comfortable
Home-page: https://github.com/TorDataScientist/PyTDP
Author: TorDataScientist
License: MIT License
Platform: UNKNOWN
License-File: LICENSE
Requires-Dist: googletrans (==4.0.0-rc1)
Requires-Dist: pandas (==1.1.5)
Requires-Dist: scikit-learn (==0.22.2)
Requires-Dist: joblib (==1.0.1)
